LICENSE
MANIFEST.in
README.md
requirements.txt
setup.py
ATACFragQC/__init__.py
ATACFragQC/__main__.py
ATACFragQC.egg-info/PKG-INFO
ATACFragQC.egg-info/SOURCES.txt
ATACFragQC.egg-info/dependency_links.txt
ATACFragQC.egg-info/entry_points.txt
ATACFragQC.egg-info/requires.txt
ATACFragQC.egg-info/top_level.txt