Metadata-Version: 2.1
Name: ATACFragQC
Version: 0.4.5
Summary: Fragment Quality Control for ATAC-seq
Home-page: https://github.com/0CBH0/ATACFragQC
Author: 0CBH0
Author-email: maodatou88@163.com
License: MIT
Platform: UNKNOWN
Classifier: License :: OSI Approved :: MIT License
Classifier: Programming Language :: Python
Classifier: Programming Language :: Python :: 2
Classifier: Programming Language :: Python :: 3
Requires-Python: >=3.6
License-File: LICENSE
